{
  "FireworksParty": {
    "Datas": [
      {
        "ID": 10000,
        "Path": "System/FireworksParty/烟火大会01.prefab"
      },
      {
        "ID": 10001,
        "Path": "System/FireworksParty/烟火大会01.prefab"
      },
      {
        "ID": 10002,
        "Path": "System/FireworksParty/烟火大会01.prefab"
      },
      {
        "ID": 10003,
        "Path": "System/FireworksParty/烟火大会01.prefab"
      },
      {
        "ID": 10004,
        "Path": "System/FireworksParty/烟火大会01.prefab"
      },
      {
        "ID": 10005,
        "Path": "System/FireworksParty/烟火大会01.prefab"
      }
    ]
  }
}