{
  "GemDuelAchieve": {
    "Datas": [
      {
        "ID": 100001,
        "CountParam": 3
      },
      {
        "ID": 100002,
        "CountParam": 5
      },
      {
        "ID": 100003,
        "CountParam": 10
      },
      {
        "ID": 100004,
        "CountParam": 20
      },
      {
        "ID": 100005,
        "CountParam": 30
      },
      {
        "ID": 100006,
        "CountParam": 40
      },
      {
        "ID": 100007,
        "CountParam": 50
      },
      {
        "ID": 100008,
        "CountParam": 60
      },
      {
        "ID": 100009,
        "CountParam": 70
      },
      {
        "ID": 100010,
        "CountParam": 80
      },
      {
        "ID": 100011,
        "CountParam": 90
      },
      {
        "ID": 100012,
        "CountParam": 100
      },
      {
        "ID": 100013,
        "CountParam": 110
      },
      {
        "ID": 100014,
        "CountParam": 120
      },
      {
        "ID": 100101,
        "CountParam": 2
      },
      {
        "ID": 100102,
        "CountParam": 3
      },
      {
        "ID": 100103,
        "CountParam": 4
      },
      {
        "ID": 100104,
        "CountParam": 8
      },
      {
        "ID": 100105,
        "CountParam": 15
      },
      {
        "ID": 100106,
        "CountParam": 20
      },
      {
        "ID": 100107,
        "CountParam": 40
      },
      {
        "ID": 100108,
        "CountParam": 80
      },
      {
        "ID": 100109,
        "CountParam": 100
      },
      {
        "ID": 100110,
        "CountParam": 200
      },
      {
        "ID": 100111,
        "CountParam": 300
      },
      {
        "ID": 410001,
        "CountParam": 1
      },
      {
        "ID": 410002,
        "CountParam": 3
      },
      {
        "ID": 410003,
        "CountParam": 4
      },
      {
        "ID": 410004,
        "CountParam": 5
      },
      {
        "ID": 410005,
        "CountParam": 1
      },
      {
        "ID": 410006,
        "CountParam": 2
      },
      {
        "ID": 410201,
        "CountParam": 1
      },
      {
        "ID": 410202,
        "CountParam": 2
      },
      {
        "ID": 410203,
        "CountParam": 3
      },
      {
        "ID": 410204,
        "CountParam": 4
      },
      {
        "ID": 410205,
        "CountParam": 5
      },
      {
        "ID": 410206,
        "CountParam": 6
      },
      {
        "ID": 200001,
        "Param": [
          1015
        ],
        "CountParam": 1
      },
      {
        "ID": 200002,
        "Param": [
          2015
        ],
        "CountParam": 1
      },
      {
        "ID": 3000011,
        "Param": [
          1001
        ],
        "CountParam": 8
      },
      {
        "ID": 3000012,
        "Param": [
          1002
        ],
        "CountParam": 12
      },
      {
        "ID": 3000013,
        "Param": [
          1003
        ],
        "CountParam": 9
      }
    ]
  }
}